{
  "strategy": "Sequential Analysis with Overlap Validation",
  "phases": {
    "phase_1_historical": {
      "period": "2002-2017",
      "primary_dataset": "GRACE",
      "analysis_type": "Historical trend analysis",
      "key_insights": [
        "Long-term groundwater depletion trends",
        "Seasonal patterns and cycles",
        "Impact of major droughts/floods",
        "Baseline groundwater status"
      ]
    },
    "phase_2_recent": {
      "period": "2018-2024",
      "primary_dataset": "GLDAS",
      "analysis_type": "Current status assessment",
      "key_insights": [
        "Recent groundwater trends",
        "Climate change impacts",
        "Current water stress levels",
        "Post-2018 policy impacts"
      ]
    },
    "phase_3_integrated": {
      "period": "2002-2024",
      "methodology": "Combined trend analysis",
      "challenges": [
        "Different measurement units (cm vs m\u00b3/m\u00b3)",
        "Different spatial resolutions",
        "Data gap in 2017-2018"
      ],
      "solutions": [
        "Normalize both datasets to z-scores",
        "Focus on relative trends rather than absolute values",
        "Statistical correlation during overlap period"
      ]
    }
  }
}